imghdr2/__init__.py
imghdr2-3.11.dist-info/LICENSE
imghdr2-3.11.dist-info/METADATA
imghdr2-3.11.dist-info/WHEEL
imghdr2-3.11.dist-info/top_level.txt
imghdr2-3.11.dist-info/RECORD
