Metadata-Version: 2.1
Name: imghdr2
Version: 3.11
Summary: A lightweight Python library for determining the type of image files, as a separate module due to official deprecation.
Author-email: "Python core team, packaged by Jeremy Howard" <info@fast.ai>
License: 1. This LICENSE AGREEMENT is between the Python Software Foundation ("PSF"), and
Project-URL: Homepage, https://github.com/answerdotai/imghdr2
Project-URL: Bug Tracker, https://github.com/answerdotai/imghdr2/issues
Project-URL: Source Code, https://github.com/answerdotai/imghdr2
Keywords: image,type,detection,imghdr2,imghdr
Classifier: Development Status :: 5 - Production/Stable
Classifier: Intended Audience :: Developers
Classifier: License :: OSI Approved :: Python Software Foundation License
Classifier: Operating System :: OS Independent
Classifier: Topic :: Software Development :: Libraries :: Python Modules
Classifier: Topic :: Multimedia :: Graphics
Requires-Python: >=3.6
License-File: LICENSE
